cnxns/__init__.py
cnxns/dataverse.py
cnxns/dbms.py
cnxns-0.0.2.dist-info/licenses/LICENSE
cnxns-0.0.2.dist-info/METADATA
cnxns-0.0.2.dist-info/WHEEL
cnxns-0.0.2.dist-info/top_level.txt
cnxns-0.0.2.dist-info/RECORD
