Metadata-Version: 2.4
Name: cnxns
Version: 0.0.2
Summary: Wrappers for connecting to data systems
Author-email: n3ddu8 <n3ddu8@proton.me>
License-Expression: MIT
Project-URL: Homepage, https://github.com/n3ddu8/cnxns
Project-URL: Issues, https://github.com/n3ddu8/cnxns/issues
Classifier: Programming Language :: Python :: 3
Classifier: Operating System :: OS Independent
Requires-Python: >=3.9
License-File: LICENSE
Requires-Dist: pyodbc>=5.2.0
Requires-Dist: sqlalchemy>=2.0.43
Requires-Dist: pandas>=2.3.2
Requires-Dist: msal==1.20.0b1
Dynamic: license-file
